bmoviesdk/__init__.py
bmoviesdk/movies_client.py
bmoviesdk/movies_config.py
bmoviesdk/schemas/__init__.py
bmoviesdk/schemas/schemas.py
bmoviesdk-0.0.2.dist-info/METADATA
bmoviesdk-0.0.2.dist-info/WHEEL
bmoviesdk-0.0.2.dist-info/top_level.txt
bmoviesdk-0.0.2.dist-info/RECORD
