Metadata-Version: 2.4
Name: bmoviesdk
Version: 0.0.2
Summary: Accédez et manipulez les données de l’API MovieLens avec ce SDK Python léger, pensé pour tous ceux qui travaillent avec la data, qu’ils soient débutants ou expérimentés.
Author: [Borice DOSSOU]
Classifier: Development Status :: 3 - Alpha
Classifier: Programming Language :: Python :: 3
Classifier: License :: OSI Approved :: MIT License
Classifier: Operating System :: OS Independent
Requires-Python: >=3.13
Requires-Dist: httpx>=0.28.1
Requires-Dist: pydantic>=2.12.5
Requires-Dist: backoff>=2.2.1
Requires-Dist: numpy>=2.2.4
Requires-Dist: pandas>=2.2.3
Requires-Dist: python-dotenv
